{"is_source_file": true, "format": "Dart", "description": "Defines the 'Note' class representing a note object within the application, including serialization methods and properties.", "external_files": ["tag.dart"], "external_methods": ["DateTime.parse()", "DateTime.toIso8601String()"], "published": ["Note"], "classes": [{"name": "Note", "description": "Represents a note with properties such as id, title, content, timestamps, and associated tags, with methods for serialization and copying."}], "methods": [{"name": "toMap", "description": "Converts the Note object into a Map suitable for database storage."}, {"name": "fromMap", "description": "Factory constructor to create a Note instance from a Map, with optional tags."}, {"name": "copyWith", "description": "Creates a copy of the Note instance with optional new values for its properties."}], "calls": ["DateTime.parse()", "DateTime.toIso8601String()"], "search-terms": ["Note class", "note.dart", "serialization", "toMap", "fromMap", "copyWith", "tags"], "state": 2, "file_id": 20, "knowledge_revision": 42, "git_revision": "", "hash": "7403211713bb1e3527cc40292ca242ae", "format-version": 4, "code-base-name": "notes_frontend", "filename": "notes_frontend/lib/models/note.dart", "revision_history": [{"42": ""}]}